phd_scraper/__init__.py
phd_scraper/__main__.py
phd_scraper/models.py
phd_scraper/scraper.py
phd_scraper/utils.py
academic_phd_scraper-1.0.0.dist-info/METADATA
academic_phd_scraper-1.0.0.dist-info/WHEEL
academic_phd_scraper-1.0.0.dist-info/entry_points.txt
academic_phd_scraper-1.0.0.dist-info/top_level.txt
academic_phd_scraper-1.0.0.dist-info/RECORD
