Metadata-Version: 2.4
Name: academic-phd-scraper
Version: 1.0.0
Summary: A Python module to scrape PhD offers from academicpositions.com
Author-email: PhD Finder <contact@example.com>
License-Expression: MIT
Keywords: phd,academic,scraper,positions,jobs,academicpositions
Classifier: Development Status :: 4 - Beta
Classifier: Intended Audience :: Science/Research
Classifier: Operating System :: OS Independent
Classifier: Programming Language :: Python :: 3
Classifier: Programming Language :: Python :: 3.8
Classifier: Programming Language :: Python :: 3.9
Classifier: Programming Language :: Python :: 3.10
Classifier: Programming Language :: Python :: 3.11
Classifier: Programming Language :: Python :: 3.12
Classifier: Topic :: Internet :: WWW/HTTP :: Indexing/Search
Classifier: Topic :: Scientific/Engineering
Requires-Python: >=3.8
Requires-Dist: requests>=2.28.0
Requires-Dist: beautifulsoup4>=4.11.0
Provides-Extra: dev
Requires-Dist: pytest>=7.0.0; extra == "dev"
Requires-Dist: pytest-cov>=4.0.0; extra == "dev"
Requires-Dist: black>=23.0.0; extra == "dev"
Requires-Dist: ruff>=0.1.0; extra == "dev"
